{
  "posts": [
    {
      "id": 1,
      "title": "json-server",
      "author": "typicode"
    }
  ],
  "comments": [
    {
      "id": 1,
      "body": "some comment",
      "postId": 1
    },
    {
      "body": "some comment11111",
      "postId": 1,
      "id": 2
    }
  ],
  "profile": {
    "name": "typicode"
  },
  "puzzle": [
    {
      "retro": "jsjsjjs",
      "id": 1,
      "src": 8888
    },
    {
      "ser": "hhhhhh",
      "id": 2
    },
    {
      "ser": "hhhhhh",
      "id": 3
    },
    {
      "src": "img",
      "rows": 2,
      "cols": 3,
      "id": 4
    },
    {
      "data": "something else",
      "id": 5
    },
    {
      "data": "something else",
      "id": 6
    },
    {
      "data": "something else",
      "id": 7
    },
    {
      "data": "something else",
      "id": 8
    },
    {
      "data": "something else",
      "id": 9
    },
    {
      "data": "something else",
      "id": 10
    },
    {
      "data": "something else",
      "id": 11
    },
    {
      "data": "something elseggggggggggg",
      "id": 12
    },
    {
      "data": "something elseggggggggggg",
      "id": 13
    },
    {
      "data": "something elseggggggggggg",
      "id": 14
    },
    {
      "der": "data",
      "id": 15
    },
    {
      "data": "something elseggggggggggg",
      "id": 16
    },
    {
      "data": {
        "src": "http://gifsec.com/wp-content/uploads/GIF/2014/05/Cute-girl-gif.gif?gs=a",
        "rows": "3",
        "cols": "3"
      },
      "id": 17
    },
    {
      "data": "something elseggggggggggg",
      "id": 18
    },
    {
      "data": {
        "src": "http://gifsec.com/wp-content/uploads/GIF/2014/05/Cute-girl-gif.gif?gs=a",
        "rows": "3",
        "cols": "3"
      },
      "id": 19
    },
    {
      "data": {
        "src": "http://gifsec.com/wp-content/uploads/2014/03/Hot-girl-GIF.gif",
        "rows": "2",
        "cols": "2"
      },
      "id": 20
    },
    {
      "data": "something elseggggggggggg",
      "id": 21
    },
    {
      "data": "something elseggggggggggg",
      "id": 22
    },
    {
      "data": "something elseggggggggggg",
      "id": 23
    },
    {
      "data": "something elseggggggggggg",
      "id": 24
    },
    {
      "data": "something elseggggggggggg",
      "id": 25
    },
    {
      "data": "something elseggggggggggg",
      "id": 26
    },
    {
      "data": "something elseggggggggggg",
      "id": 27
    },
    {
      "data": "something elseggggggggggg",
      "id": 28
    },
    {
      "data": "something elseggggggggggg",
      "id": 29
    },
    {
      "data": "something elseggggggggggg",
      "id": 30
    },
    {
      "data": "something elseggggggggggg",
      "id": 31
    },
    {
      "data": "something elseggggggggggg",
      "id": 32
    },
    {
      "data": "something elseggggggggggg",
      "id": 33
    },
    {
      "data": "something elseggggggggggg",
      "id": 34
    },
    {
      "data": "something elseggggggggggg",
      "id": 35
    },
    {
      "data": "something elseggggggggggg",
      "id": 36
    },
    {
      "data": "something elseggggggggggg",
      "id": 37
    },
    {
      "data": "something elseggggggggggg",
      "id": 38
    },
    {
      "data": "something elseggggggggggg",
      "id": 39
    },
    {
      "data": "something elseggggggggggg",
      "id": 40
    },
    {
      "data": "something elseggggggggggg",
      "id": 41
    },
    {
      "data": "something elseggggggggggg",
      "id": 42
    },
    {
      "data": "something elseggggggggggg",
      "id": 43
    },
    {
      "data": "something elseggggggggggg",
      "id": 44
    },
    {
      "data": "something elseggggggggggg",
      "id": 45
    },
    {
      "data": "something elseggggggggggg",
      "id": 46
    },
    {
      "data": "something elseggggggggggg",
      "id": 47
    },
    {
      "data": "something elseggggggggggg",
      "id": 48
    },
    {
      "data": "something elseggggggggggg",
      "id": 49
    },
    {
      "data": {
        "src": "http://gifsec.com/wp-content/uploads/GIF/2014/05/Hot-gir-reaction-gif.gif?gs=a",
        "rows": "3",
        "cols": "3"
      },
      "id": 50
    },
    {
      "data": "something elseggggggggggg",
      "id": 51
    },
    {
      "data": "something elseggggggggggg",
      "id": 52
    },
    {
      "data": "something elseggggggggggg",
      "id": 53
    },
    {
      "data": "something elseggggggggggg",
      "id": 54
    },
    {
      "data": "something elseggggggggggg",
      "id": 55
    },
    {
      "data": {
        "src": "https://media.giphy.com/media/XVClGdLeBGyZO/giphy.gif",
        "rows": 4,
        "cols": 2
      },
      "id": 56
    },
    {
      "data": {
        "src": "http://www.gifbin.com/bin/072011/reverse-1313397603_spinning_girl.gif",
        "rows": 4,
        "cols": 3
      },
      "id": 57
    },
    {
      "data": {
        "src": "http://s5.favim.com/orig/141115/2009-beautiful-black-and-white-crazy-Favim.com-2239225.gif",
        "rows": 3,
        "cols": 3
      },
      "id": 58
    },
    {
      "data": {
        "src": "http://www.lovethisgif.com/uploaded_images/11829-Arizona-Iowa-Stop-Girl-Gif-Pandawhale.gif",
        "rows": 3,
        "cols": 3
      },
      "id": 59
    },
    {
      "data": {
        "src": "https://media.giphy.com/media/nr6Uz7bTJo9uE/giphy.gif",
        "rows": 3,
        "cols": 3
      },
      "id": 60
    },
    {
      "data": {
        "rows": 5,
        "cols": 5,
        "src": "https://media.giphy.com/media/1YXNO3SdQ0FrO/giphy.gif"
      },
      "id": 61
    },
    {
      "data": {
        "rows": 3,
        "cols": 4,
        "src": "http://gifsec.com/wp-content/uploads/GIF/2014/03/Wink-Girl-GIF.gif?gs=a"
      },
      "id": 62
    },
    {
      "data": {
        "src": "http://i1268.photobucket.com/albums/jj561/phess92/GIFs/df68fffc.gif",
        "rows": 1,
        "cols": 1
      },
      "id": 63
    },
    {
      "data": {
        "src": "http://i1268.photobucket.com/albums/jj561/phess92/GIFs/df68fffc.gif",
        "rows": 2,
        "cols": 2
      },
      "id": 64
    },
    {
      "data": {
        "src": "https://65.media.tumblr.com/d60859ace82d526294e21e6d2b8dd5cb/tumblr_inline_ob35hpc7bZ1tmd0r8_500.gif",
        "rows": 2,
        "cols": 3
      },
      "id": 65
    }
  ]
}